anovate_ai_cli/__init__.py
anovate_ai_cli/__main__.py
anovate_ai_cli/anovate_ai_cli.py
anovate_ai_cli-0.1.2.dist-info/METADATA
anovate_ai_cli-0.1.2.dist-info/WHEEL
anovate_ai_cli-0.1.2.dist-info/entry_points.txt
anovate_ai_cli-0.1.2.dist-info/RECORD
